bigquery_erd/__init__.py
bigquery_erd/bigquery.py
bigquery_erd/utils.py
bigquery_erd-0.1.1.dist-info/LICENSE.md
bigquery_erd-0.1.1.dist-info/WHEEL
bigquery_erd-0.1.1.dist-info/METADATA
bigquery_erd-0.1.1.dist-info/RECORD
