Metadata-Version: 2.1
Name: bigquery-erd
Version: 0.1.1
Summary: Building Entity Relationship Diagrams for Google BigQuery.
License: MIT
Author: Jan-Benedikt Jagusch
Author-email: jan.jagusch@gmail.com
Requires-Python: >=3.8,<4.0
Classifier: License :: OSI Approved :: MIT License
Classifier: Programming Language :: Python :: 3
Classifier: Programming Language :: Python :: 3.8
Classifier: Programming Language :: Python :: 3.9
Requires-Dist: ERAlchemy (>=1.2.10,<2.0.0)
Requires-Dist: google-cloud-bigquery (>=2.4.0,<3.0.0)
